pyide_sdk/__init__.py
pyide_sdk/api.py
pyide_sdk/decorators.py
pyide_sdk/hooks.py
pyide_sdk/plugin.py
pyide_sdk/types.py
pyide_sdk/ui.py
pyide_sdk-1.0.1.dist-info/licenses/LICENSE
pyide_sdk-1.0.1.dist-info/METADATA
pyide_sdk-1.0.1.dist-info/WHEEL
pyide_sdk-1.0.1.dist-info/top_level.txt
pyide_sdk-1.0.1.dist-info/RECORD
