Metadata-Version: 2.4
Name: pyide-sdk
Version: 1.0.1
Summary: Plugin SDK for PyIDE - Create extensions and plugins for PyIDE
Home-page: https://github.com/AeonLtd/pyide-sdk
Author: PyIDE Team
Author-email: PyIDE Team <support@pyide.org>
Maintainer-email: PyIDE Team <support@pyide.org>
License: MIT
Project-URL: Homepage, https://github.com/AeonLtd/pyide-sdk
Project-URL: Documentation, https://github.com/AeonLtd/pyide-sdk#readme
Project-URL: Repository, https://github.com/AeonLtd/pyide-sdk.git
Project-URL: Issues, https://github.com/AeonLtd/pyide-sdk/issues
Keywords: pyide,plugin,sdk,ide,extension,python,development
Classifier: Development Status :: 4 - Beta
Classifier: Intended Audience :: Developers
Classifier: License :: OSI Approved :: MIT License
Classifier: Operating System :: OS Independent
Classifier: Programming Language :: Python :: 3
Classifier: Programming Language :: Python :: 3.8
Classifier: Programming Language :: Python :: 3.9
Classifier: Programming Language :: Python :: 3.10
Classifier: Programming Language :: Python :: 3.11
Classifier: Programming Language :: Python :: 3.12
Classifier: Topic :: Software Development :: Libraries :: Python Modules
Classifier: Topic :: Text Editors :: Integrated Development Environments (IDE)
Requires-Python: >=3.8
License-File: LICENSE
Provides-Extra: dev
Requires-Dist: pytest>=7.0; extra == "dev"
Requires-Dist: pytest-asyncio>=0.21; extra == "dev"
Requires-Dist: black>=23.0; extra == "dev"
Requires-Dist: mypy>=1.0; extra == "dev"
Requires-Dist: ruff>=0.1.0; extra == "dev"
Dynamic: author
Dynamic: home-page
Dynamic: license-file
Dynamic: requires-python
